bricklib/__init__.py
bricklib/mixins.py
bricklib/types.py
bricklib-0.1.1.dist-info/METADATA
bricklib-0.1.1.dist-info/WHEEL
bricklib-0.1.1.dist-info/RECORD
