Metadata-Version: 2.1
Name: bricklib
Version: 0.1.1
Summary: Augment your Python objects with drop-in behaviours and signals
Home-page: https://github.com/zdeyn/bricklib
Author: zdeyn
Author-email: zdeyn@zdeyn.com
Requires-Python: >=3.10,<4.0
Classifier: Programming Language :: Python :: 3
Classifier: Programming Language :: Python :: 3.10
Classifier: Programming Language :: Python :: 3.11
Classifier: Programming Language :: Python :: 3.12
Project-URL: Repository, https://github.com/zdeyn/bricklib
